<?xml version="1.0" encoding="utf-8" ?>
<dwsync>
<file name="DB.php" server="192.168.56.101" local="130464657870000000" remote="130751544600000000" Dst="0" />
<file name="DB_cache.php" server="192.168.56.101" local="130464657870000000" remote="130751544600000000" Dst="0" />
<file name="DB_active_rec.php" server="192.168.56.101" local="130464657870000000" remote="130751544600000000" Dst="0" />
<file name="DB_driver.php" server="192.168.56.101" local="130464657870000000" remote="130751544600000000" Dst="0" />
<file name="DB_forge.php" server="192.168.56.101" local="130464657870000000" remote="130751544600000000" Dst="0" />
<file name="DB_result.php" server="192.168.56.101" local="130464657870000000" remote="130751544600000000" Dst="0" />
<file name="DB_utility.php" server="192.168.56.101" local="130464657870000000" remote="130751544600000000" Dst="0" />
<file name="index.html" server="192.168.56.101" local="129664507580000000" remote="130751544600000000" Dst="0" />
</dwsync>